[
{
"asset_id":
"36945847-3a2f-44f8-b15b-8e7fe12d01d4",
"blob":
"da34913a-c9f2-4698-a558-449122111b06",
"created":
"2023-07-04T14:38:07.517939+00:00",
"metadata":
{
"@context":
"https://raw.githubusercontent.com/dandi/schema/master/releases/0.6.4/context.json",
"access":
[
{
"schemaKey":
"AccessRequirements",
"status":
"dandi:OpenAccess"
}
],
"approach":
[
{
"name":
"behavioral approach",
"schemaKey":
"ApproachType"
},
{
"name":
"electrophysiological approach",
"schemaKey":
"ApproachType"
}
],
"blobDateModified":
"2023-07-04T15:08:13.658576+02:00",
"contentSize":
314241144,
"contentUrl":
[
"https://api.dandiarchive.org/api/assets/36945847-3a2f-44f8-b15b-8e7fe12d01d4/download/",
"https://dandiarchive.s3.amazonaws.com/blobs/da3/491/da34913a-c9f2-4698-a558-449122111b06"
],
"dateModified":
"2023-07-04T16:21:38.313083+02:00",
"digest":
{
"dandi:dandi-etag":
"c3460041004ce8ad227c968def599984-5",
"dandi:sha2-256":
"576e195702557e3ca1f5f8286acb36588de823b281bada5050259f6328a0b58b"
},
"encodingFormat":
"application/x-nwb",
"id":
"dandiasset:36945847-3a2f-44f8-b15b-8e7fe12d01d4",
"identifier":
"36945847-3a2f-44f8-b15b-8e7fe12d01d4",
"keywords":
[
"Neuroscience",
"Electrophysiology",
"Human",
"Awake",
"Local field potential",
"Neuronal action potential",
"Spikes",
"Medial temporal lobe",
"Hippocampus",
"Entorhinal cortex",
"Amygdala",
"Scalp EEG",
"Intracranial EEG",
"Cognitive task",
"Verbal working memory",
"Epilepsy"
],
"measurementTechnique":
[
{
"name":
"analytical technique",
"schemaKey":
"MeasurementTechniqueType"
},
{
"name":
"signal filtering technique",
"schemaKey":
"MeasurementTechniqueType"
},
{
"name":
"behavioral technique",
"schemaKey":
"MeasurementTechniqueType"
},
{
"name":
"surgical technique",
"schemaKey":
"MeasurementTechniqueType"
},
{
"name":
"spike sorting technique",
"schemaKey":
"MeasurementTechniqueType"
},
{
"name":
"multi electrode extracellular electrophysiology recording technique",
"schemaKey":
"MeasurementTechniqueType"
}
],
"path":
"sub-01/sub-01_ses-20161214T171300_behavior+ecephys.nwb",
"schemaKey":
"Asset",
"schemaVersion":
"0.6.4",
"variableMeasured":
[
{
"schemaKey":
"PropertyValue",
"value":
"Units"
},
{
"schemaKey":
"PropertyValue",
"value":
"LFP"
},
{
"schemaKey":
"PropertyValue",
"value":
"ElectricalSeries"
},
{
"schemaKey":
"PropertyValue",
"value":
"ElectrodeGroup"
},
{
"schemaKey":
"PropertyValue",
"value":
"BehavioralEvents"
},
{
"schemaKey":
"PropertyValue",
"value":
"ProcessingModule"
}
],
"wasAttributedTo":
[
{
"age":
{
"schemaKey":
"PropertyValue",
"unitText":
"ISO-8601 duration",
"value":
"P24Y",
"valueReference":
{
"schemaKey":
"PropertyValue",
"value":
"dandi:BirthReference"
}
},
"identifier":
"01",
"schemaKey":
"Participant",
"sex":
{
"identifier":
"http://purl.obolibrary.org/obo/PATO_0000383",
"name":
"Female",
"schemaKey":
"SexType"
},
"species":
{
"identifier":
"http://purl.obolibrary.org/obo/NCBITaxon_9606",
"name":
"Homo sapiens - Human",
"schemaKey":
"SpeciesType"
}
}
],
"wasGeneratedBy":
[
{
"description":
"Running experiment as described in the the experiment description",
"name":
"Acquisition session",
"schemaKey":
"Session",
"startDate":
"2016-12-14T17:13:00+01:00"
},
{
"description":
"Metadata generated by DANDI cli",
"endDate":
"2023-07-04T16:21:38.313083+02:00",
"id":
"urn:uuid:64522e4f-4bbb-4990-940e-48356c5025a6",
"name":
"Metadata generation",
"schemaKey":
"Activity",
"startDate":
"2023-07-04T16:21:37.678115+02:00",
"wasAssociatedWith":
[
{
"identifier":
"RRID:SCR_019009",
"name":
"DANDI Command Line Interface",
"schemaKey":
"Software",
"url":
"https://github.com/dandi/dandi-cli",
"version":
"0.55.1"
}
]
}
]
},
"modified":
"2023-07-04T14:38:11.391887+00:00",
"path":
"sub-01/sub-01_ses-20161214T171300_behavior+ecephys.nwb",
"size":
314241144
},
{
"asset_id":
"74471dd6-fafc-49ec-8aca-fdaf295091ee",
"blob":
"d72fe5c2-3e94-4f04-bdb2-1979d0ef6d2c",
"created":
"2023-07-04T14:42:00.349113+00:00",
"metadata":
{
"@context":
"https://raw.githubusercontent.com/dandi/schema/master/releases/0.6.4/context.json",
"access":
[
{
"schemaKey":
"AccessRequirements",
"status":
"dandi:OpenAccess"
}
],
"approach":
[
{
"name":
"behavioral approach",
"schemaKey":
"ApproachType"
},
{
"name":
"electrophysiological approach",
"schemaKey":
"ApproachType"
}
],
"blobDateModified":
"2023-07-04T15:08:42.324367+02:00",
"contentSize":
314234029,
"contentUrl":
[
"https://api.dandiarchive.org/api/assets/74471dd6-fafc-49ec-8aca-fdaf295091ee/download/",
"https://dandiarchive.s3.amazonaws.com/blobs/d72/fe5/d72fe5c2-3e94-4f04-bdb2-1979d0ef6d2c"
],
"dateModified":
"2023-07-04T16:21:39.545175+02:00",
"digest":
{
"dandi:dandi-etag":
"869ec3b71f5902ceed0d92e36bc77d5c-5",
"dandi:sha2-256":
"81f5fecfb6cd7db4d44c03f7dd014c36eef1ae686ecd9077b3455a492a066326"
},
"encodingFormat":
"application/x-nwb",
"id":
"dandiasset:74471dd6-fafc-49ec-8aca-fdaf295091ee",
"identifier":
"74471dd6-fafc-49ec-8aca-fdaf295091ee",
"keywords":
[
"Neuroscience",
"Electrophysiology",
"Human",
"Awake",
"Local field potential",
"Neuronal action potential",
"Spikes",
"Medial temporal lobe",
"Hippocampus",
"Entorhinal cortex",
"Amygdala",
"Scalp EEG",
"Intracranial EEG",
"Cognitive task",
"Verbal working memory",
"Epilepsy"
],
"measurementTechnique":
[
{
"name":
"analytical technique",
"schemaKey":
"MeasurementTechniqueType"
},
{
"name":
"signal filtering technique",
"schemaKey":
"MeasurementTechniqueType"
},
{
"name":
"behavioral technique",
"schemaKey":
"MeasurementTechniqueType"
},
{
"name":
"surgical technique",
"schemaKey":
"MeasurementTechniqueType"
},
{
"name":
"spike sorting technique",
"schemaKey":
"MeasurementTechniqueType"
},
{
"name":
"multi electrode extracellular electrophysiology recording technique",
"schemaKey":
"MeasurementTechniqueType"
}
],
"path":
"sub-01/sub-01_ses-20161214T173600_behavior+ecephys.nwb",
"schemaKey":
"Asset",
"schemaVersion":
"0.6.4",
"variableMeasured":
[
{
"schemaKey":
"PropertyValue",
"value":
"Units"
},
{
"schemaKey":
"PropertyValue",
"value":
"LFP"
},
{
"schemaKey":
"PropertyValue",
"value":
"ElectricalSeries"
},
{
"schemaKey":
"PropertyValue",
"value":
"ElectrodeGroup"
},
{
"schemaKey":
"PropertyValue",
"value":
"BehavioralEvents"
},
{
"schemaKey":
"PropertyValue",
"value":
"ProcessingModule"
}
],
"wasAttributedTo":
[
{
"age":
{
"schemaKey":
"PropertyValue",
"unitText":
"ISO-8601 duration",
"value":
"P24Y",
"valueReference":
{
"schemaKey":
"PropertyValue",
"value":
"dandi:BirthReference"
}
},
"identifier":
"01",
"schemaKey":
"Participant",
"sex":
{
"identifier":
"http://purl.obolibrary.org/obo/PATO_0000383",
"name":
"Female",
"schemaKey":
"SexType"
},
"species":
{
"identifier":
"http://purl.obolibrary.org/obo/NCBITaxon_9606",
"name":
"Homo sapiens - Human",
"schemaKey":
"SpeciesType"
}
}
],
"wasGeneratedBy":
[
{
"description":
"Running experiment as described in the the experiment description",
"name":
"Acquisition session",
"schemaKey":
"Session",
"startDate":
"2016-12-14T17:36:00+01:00"
},
{
"description":
"Metadata generated by DANDI cli",
"endDate":
"2023-07-04T16:21:39.545175+02:00",
"id":
"urn:uuid:23768f6d-8623-40e5-b437-e869a9d99a89",
"name":
"Metadata generation",
"schemaKey":
"Activity",
"startDate":
"2023-07-04T16:21:38.515119+02:00",
"wasAssociatedWith":
[
{
"identifier":
"RRID:SCR_019009",
"name":
"DANDI Command Line Interface",
"schemaKey":
"Software",
"url":
"https://github.com/dandi/dandi-cli",
"version":
"0.55.1"
}
]
}
]
},
"modified":
"2023-07-04T14:42:04.146626+00:00",
"path":
"sub-01/sub-01_ses-20161214T173600_behavior+ecephys.nwb",
"size":
314234029
},
{
"asset_id":
"e53efb0c-a508-4953-b932-e320e1217066",
"blob":
"b600d1e7-11c5-4c63-89d6-b569eeaf42cf",
"created":
"2023-07-04T14:53:31.628232+00:00",
"metadata":
{
"@context":
"https://raw.githubusercontent.com/dandi/schema/master/releases/0.6.4/context.json",
"access":
[
{
"schemaKey":
"AccessRequirements",
"status":
"dandi:OpenAccess"
}
],
"approach":
[
{
"name":
"behavioral approach",
"schemaKey":
"ApproachType"
},
{
"name":
"electrophysiological approach",
"schemaKey":
"ApproachType"
}
],
"blobDateModified":
"2023-07-04T15:09:04.113106+02:00",
"contentSize":
313059099,
"contentUrl":
[
"https://api.dandiarchive.org/api/assets/e53efb0c-a508-4953-b932-e320e1217066/download/",
"https://dandiarchive.s3.amazonaws.com/blobs/b60/0d1/b600d1e7-11c5-4c63-89d6-b569eeaf42cf"
],
"dateModified":
"2023-07-04T16:21:40.115278+02:00",
"digest":
{
"dandi:dandi-etag":
"d23352fafb2e18dd65545df75e82f9d7-5",
"dandi:sha2-256":
"dd1a4f7b5144083f27ad07a7291d78e01a181534561cf31aedd0a7f5e140f021"
},
"encodingFormat":
"application/x-nwb",
"id":
"dandiasset:e53efb0c-a508-4953-b932-e320e1217066",
"identifier":
"e53efb0c-a508-4953-b932-e320e1217066",
"keywords":
[
"Neuroscience",
"Electrophysiology",
"Human",
"Awake",
"Local field potential",
"Neuronal action potential",
"Spikes",
"Medial temporal lobe",
"Hippocampus",
"Entorhinal cortex",
"Amygdala",
"Scalp EEG",
"Intracranial EEG",
"Cognitive task",
"Verbal working memory",
"Epilepsy"
],
"measurementTechnique":
[
{
"name":
"analytical technique",
"schemaKey":
"MeasurementTechniqueType"
},
{
"name":
"signal filtering technique",
"schemaKey":
"MeasurementTechniqueType"
},
{
"name":
"behavioral technique",
"schemaKey":
"MeasurementTechniqueType"
},
{
"name":
"surgical technique",
"schemaKey":
"MeasurementTechniqueType"
},
{
"name":
"multi electrode extracellular electrophysiology recording technique",
"schemaKey":
"MeasurementTechniqueType"
}
],
"path":
"sub-01/sub-01_ses-20161217T121400_behavior+ecephys.nwb",
"schemaKey":
"Asset",
"schemaVersion":
"0.6.4",
"variableMeasured":
[
{
"schemaKey":
"PropertyValue",
"value":
"LFP"
},
{
"schemaKey":
"PropertyValue",
"value":
"ElectricalSeries"
},
{
"schemaKey":
"PropertyValue",
"value":
"ElectrodeGroup"
},
{
"schemaKey":
"PropertyValue",
"value":
"BehavioralEvents"
},
{
"schemaKey":
"PropertyValue",
"value":
"ProcessingModule"
}
],
"wasAttributedTo":
[
{
"age":
{
"schemaKey":
"PropertyValue",
"unitText":
"ISO-8601 duration",
"value":
"P24Y",
"valueReference":
{
"schemaKey":
"PropertyValue",
"value":
"dandi:BirthReference"
}
},
"identifier":
"01",
"schemaKey":
"Participant",
"sex":
{
"identifier":
"http://purl.obolibrary.org/obo/PATO_0000383",
"name":
"Female",
"schemaKey":
"SexType"
},
"species":
{
"identifier":
"http://purl.obolibrary.org/obo/NCBITaxon_9606",
"name":
"Homo sapiens - Human",
"schemaKey":
"SpeciesType"
}
}
],
"wasGeneratedBy":
[
{
"description":
"Running experiment as described in the the experiment description",
"name":
"Acquisition session",
"schemaKey":
"Session",
"startDate":
"2016-12-17T12:14:00+01:00"
},
{
"description":
"Metadata generated by DANDI cli",
"endDate":
"2023-07-04T16:21:40.115278+02:00",
"id":
"urn:uuid:4ac2a511-d62a-4aac-91e6-3d52d13bc6dd",
"name":
"Metadata generation",
"schemaKey":
"Activity",
"startDate":
"2023-07-04T16:21:39.077794+02:00",
"wasAssociatedWith":
[
{
"identifier":
"RRID:SCR_019009",
"name":
"DANDI Command Line Interface",
"schemaKey":
"Software",
"url":
"https://github.com/dandi/dandi-cli",
"version":
"0.55.1"
}
]
}
]
},
"modified":
"2023-07-04T14:53:33.850391+00:00",
"path":
"sub-01/sub-01_ses-20161217T121400_behavior+ecephys.nwb",
"size":
313059099
},
{
"asset_id":
"295c67aa-0af4-446d-b93a-23b1bae85e07",
"blob":
"fe2a148f-64c0-4132-aeb8-c95feb99cdef",
"created":
"2023-07-04T14:46:36.463898+00:00",
"metadata":
{
"@context":
"https://raw.githubusercontent.com/dandi/schema/master/releases/0.6.4/context.json",
"access":
[
{
"schemaKey":
"AccessRequirements",
"status":
"dandi:OpenAccess"
}
],
"approach":
[
{
"name":
"behavioral approach",
"schemaKey":
"ApproachType"
},
{
"name":
"electrophysiological approach",
"schemaKey":
"ApproachType"
}
],
"blobDateModified":
"2023-07-04T15:09:25.377948+02:00",
"contentSize":
313099035,
"contentUrl":
[
"https://api.dandiarchive.org/api/assets/295c67aa-0af4-446d-b93a-23b1bae85e07/download/",
"https://dandiarchive.s3.amazonaws.com/blobs/fe2/a14/fe2a148f-64c0-4132-aeb8-c95feb99cdef"
],
"dateModified":
"2023-07-04T16:21:39.695716+02:00",
"digest":
{
"dandi:dandi-etag":
"1df5599dc0924bd44ddc712fbb2483db-5",
"dandi:sha2-256":
"ede906564d6ceda3ebd816a707927bf996e2499e334bb001c1967390a8a35649"
},
"encodingFormat":
"application/x-nwb",
"id":
"dandiasset:295c67aa-0af4-446d-b93a-23b1bae85e07",
"identifier":
"295c67aa-0af4-446d-b93a-23b1bae85e07",
"keywords":
[
"Neuroscience",
"Electrophysiology",
"Human",
"Awake",
"Local field potential",
"Neuronal action potential",
"Spikes",
"Medial temporal lobe",
"Hippocampus",
"Entorhinal cortex",
"Amygdala",
"Scalp EEG",
"Intracranial EEG",
"Cognitive task",
"Verbal working memory",
"Epilepsy"
],
"measurementTechnique":
[
{
"name":
"analytical technique",
"schemaKey":
"MeasurementTechniqueType"
},
{
"name":
"signal filtering technique",
"schemaKey":
"MeasurementTechniqueType"
},
{
"name":
"behavioral technique",
"schemaKey":
"MeasurementTechniqueType"
},
{
"name":
"surgical technique",
"schemaKey":
"MeasurementTechniqueType"
},
{
"name":
"multi electrode extracellular electrophysiology recording technique",
"schemaKey":
"MeasurementTechniqueType"
}
],
"path":
"sub-01/sub-01_ses-20161217T122800_behavior+ecephys.nwb",
"schemaKey":
"Asset",
"schemaVersion":
"0.6.4",
"variableMeasured":
[
{
"schemaKey":
"PropertyValue",
"value":
"LFP"
},
{
"schemaKey":
"PropertyValue",
"value":
"ElectricalSeries"
},
{
"schemaKey":
"PropertyValue",
"value":
"ElectrodeGroup"
},
{
"schemaKey":
"PropertyValue",
"value":
"BehavioralEvents"
},
{
"schemaKey":
"PropertyValue",
"value":
"ProcessingModule"
}
],
"wasAttributedTo":
[
{
"age":
{
"schemaKey":
"PropertyValue",
"unitText":
"ISO-8601 duration",
"value":
"P24Y",
"valueReference":
{
"schemaKey":
"PropertyValue",
"value":
"dandi:BirthReference"
}
},
"identifier":
"01",
"schemaKey":
"Participant",
"sex":
{
"identifier":
"http://purl.obolibrary.org/obo/PATO_0000383",
"name":
"Female",
"schemaKey":
"SexType"
},
"species":
{
"identifier":
"http://purl.obolibrary.org/obo/NCBITaxon_9606",
"name":
"Homo sapiens - Human",
"schemaKey":
"SpeciesType"
}
}
],
"wasGeneratedBy":
[
{
"description":
"Running experiment as described in the the experiment description",
"name":
"Acquisition session",
"schemaKey":
"Session",
"startDate":
"2016-12-17T12:28:00+01:00"
},
{
"description":
"Metadata generated by DANDI cli",
"endDate":
"2023-07-04T16:21:39.695716+02:00",
"id":
"urn:uuid:48962639-f6fd-46db-bccf-83b77162bc65",
"name":
"Metadata generation",
"schemaKey":
"Activity",
"startDate":
"2023-07-04T16:21:38.734232+02:00",
"wasAssociatedWith":
[
{
"identifier":
"RRID:SCR_019009",
"name":
"DANDI Command Line Interface",
"schemaKey":
"Software",
"url":
"https://github.com/dandi/dandi-cli",
"version":
"0.55.1"
}
]
}
]
},
"modified":
"2023-07-04T14:46:39.267714+00:00",
"path":
"sub-01/sub-01_ses-20161217T122800_behavior+ecephys.nwb",
"size":
313099035
},
{
"asset_id":
"ca4f0d90-8001-493c-be32-871e4cfd3c6c",
"blob":
"93c67c19-e015-48e6-bedf-86e667da739a",
"created":
"2023-07-04T14:47:52.564368+00:00",
"metadata":
{
"@context":
"https://raw.githubusercontent.com/dandi/schema/master/releases/0.6.4/context.json",
"access":
[
{
"schemaKey":
"AccessRequirements",
"status":
"dandi:OpenAccess"
}
],
"approach":
[
{
"name":
"behavioral approach",
"schemaKey":
"ApproachType"
},
{
"name":
"electrophysiological approach",
"schemaKey":
"ApproachType"
}
],
"blobDateModified":
"2023-07-04T15:09:54.929514+02:00",
"contentSize":
397481483,
"contentUrl":
[
"https://api.dandiarchive.org/api/assets/ca4f0d90-8001-493c-be32-871e4cfd3c6c/download/",
"https://dandiarchive.s3.amazonaws.com/blobs/93c/67c/93c67c19-e015-48e6-bedf-86e667da739a"
],
"dateModified":
"2023-07-04T16:21:40.381820+02:00",
"digest":
{
"dandi:dandi-etag":
"b764cd70159325590c841fb6dea659a2-6",
"dandi:sha2-256":
"fcf529a1b8565ef348102c709c0dfde1839828a2fe3075ebbbad6f7fe1fdea91"
},
"encodingFormat":
"application/x-nwb",
"id":
"dandiasset:ca4f0d90-8001-493c-be32-871e4cfd3c6c",
"identifier":
"ca4f0d90-8001-493c-be32-871e4cfd3c6c",
"keywords":
[
"Neuroscience",
"Electrophysiology",
"Human",
"Awake",
"Local field potential",
"Neuronal action potential",
"Spikes",
"Medial temporal lobe",
"Hippocampus",
"Entorhinal cortex",
"Amygdala",
"Scalp EEG",
"Intracranial EEG",
"Cognitive task",
"Verbal working memory",
"Epilepsy"
],
"measurementTechnique":
[
{
"name":
"analytical technique",
"schemaKey":
"MeasurementTechniqueType"
},
{
"name":
"signal filtering technique",
"schemaKey":
"MeasurementTechniqueType"
},
{
"name":
"behavioral technique",
"schemaKey":
"MeasurementTechniqueType"
},
{
"name":
"surgical technique",
"schemaKey":
"MeasurementTechniqueType"
},
{
"name":
"spike sorting technique",
"schemaKey":
"MeasurementTechniqueType"
},
{
"name":
"multi electrode extracellular electrophysiology recording technique",
"schemaKey":
"MeasurementTechniqueType"
}
],
"path":
"sub-02/sub-02_ses-20160211T115600_behavior+ecephys.nwb",
"schemaKey":
"Asset",
"schemaVersion":
"0.6.4",
"variableMeasured":
[
{
"schemaKey":
"PropertyValue",
"value":
"Units"
},
{
"schemaKey":
"PropertyValue",
"value":
"LFP"
},
{
"schemaKey":
"PropertyValue",
"value":
"ElectricalSeries"
},
{
"schemaKey":
"PropertyValue",
"value":
"ElectrodeGroup"
},
{
"schemaKey":
"PropertyValue",
"value":
"BehavioralEvents"
},
{
"schemaKey":
"PropertyValue",
"value":
"ProcessingModule"
}
],
"wasAttributedTo":
[
{
"age":
{
"schemaKey":
"PropertyValue",
"unitText":
"ISO-8601 duration",
"value":
"P39Y",
"valueReference":
{
"schemaKey":
"PropertyValue",
"value":
"dandi:BirthReference"
}
},
"identifier":
"02",
"schemaKey":
"Participant",
"sex":
{
"identifier":
"http://purl.obolibrary.org/obo/PATO_0000384",
"name":
"Male",
"schemaKey":
"SexType"
},
"species":
{
"identifier":
"http://purl.obolibrary.org/obo/NCBITaxon_9606",
"name":
"Homo sapiens - Human",
"schemaKey":
"SpeciesType"
}
}
],
"wasGeneratedBy":
[
{
"description":
"Running experiment as described in the the experiment description",
"name":
"Acquisition session",
"schemaKey":
"Session",
"startDate":
"2016-02-11T11:56:00+01:00"
},
{
"description":
"Metadata generated by DANDI cli",
"endDate":
"2023-07-04T16:21:40.381820+02:00",
"id":
"urn:uuid:87dd9b38-e4c0-4401-bec7-7e843eab5104",
"name":
"Metadata generation",
"schemaKey":
"Activity",
"startDate":
"2023-07-04T16:21:39.298628+02:00",
"wasAssociatedWith":
[
{
"identifier":
"RRID:SCR_019009",
"name":
"DANDI Command Line Interface",
"schemaKey":
"Software",
"url":
"https://github.com/dandi/dandi-cli",
"version":
"0.55.1"
}
]
}
]
},
"modified":
"2023-07-04T14:47:55.818511+00:00",
"path":
"sub-02/sub-02_ses-20160211T115600_behavior+ecephys.nwb",
"size":
397481483
},
{
"asset_id":
"4dacac2e-a53a-4276-9aae-a50f4633cf58",
"blob":
"ec199eb5-b216-46f7-88ba-d940040bdaff",
"created":
"2023-07-04T14:58:06.988968+00:00",
"metadata":
{
"@context":
"https://raw.githubusercontent.com/dandi/schema/master/releases/0.6.4/context.json",
"access":
[
{
"schemaKey":
"AccessRequirements",
"status":
"dandi:OpenAccess"
}
],
"approach":
[
{
"name":
"behavioral approach",
"schemaKey":
"ApproachType"
},
{
"name":
"electrophysiological approach",
"schemaKey":
"ApproachType"
}
],
"blobDateModified":
"2023-07-04T15:10:24.397372+02:00",
"contentSize":
381140617,
"contentUrl":
[
"https://api.dandiarchive.org/api/assets/4dacac2e-a53a-4276-9aae-a50f4633cf58/download/",
"https://dandiarchive.s3.amazonaws.com/blobs/ec1/99e/ec199eb5-b216-46f7-88ba-d940040bdaff"
],
"dateModified":
"2023-07-04T16:38:10.054341+02:00",
"digest":
{
"dandi:dandi-etag":
"08c55faa4e6cf55aa9f0a0ac8dc6be51-6",
"dandi:sha2-256":
"7e46c6227975a12e166758eedbb41f5c19b3597f50b60f1a594f9d46ad5ed2d2"
},
"encodingFormat":
"application/x-nwb",
"id":
"dandiasset:4dacac2e-a53a-4276-9aae-a50f4633cf58",
"identifier":
"4dacac2e-a53a-4276-9aae-a50f4633cf58",
"keywords":
[
"Neuroscience",
"Electrophysiology",
"Human",
"Awake",
"Local field potential",
"Neuronal action potential",
"Spikes",
"Medial temporal lobe",
"Hippocampus",
"Entorhinal cortex",
"Amygdala",
"Scalp EEG",
"Intracranial EEG",
"Cognitive task",
"Verbal working memory",
"Epilepsy"
],
"measurementTechnique":
[
{
"name":
"analytical technique",
"schemaKey":
"MeasurementTechniqueType"
},
{
"name":
"signal filtering technique",
"schemaKey":
"MeasurementTechniqueType"
},
{
"name":
"behavioral technique",
"schemaKey":
"MeasurementTechniqueType"
},
{
"name":
"surgical technique",
"schemaKey":
"MeasurementTechniqueType"
},
{
"name":
"spike sorting technique",
"schemaKey":
"MeasurementTechniqueType"
},
{
"name":
"multi electrode extracellular electrophysiology recording technique",
"schemaKey":
"MeasurementTechniqueType"
}
],
"path":
"sub-02/sub-02_ses-20160211T120600_behavior+ecephys.nwb",
"schemaKey":
"Asset",
"schemaVersion":
"0.6.4",
"variableMeasured":
[
{
"schemaKey":
"PropertyValue",
"value":
"Units"
},
{
"schemaKey":
"PropertyValue",
"value":
"LFP"
},
{
"schemaKey":
"PropertyValue",
"value":
"ElectricalSeries"
},
{
"schemaKey":
"PropertyValue",
"value":
"ElectrodeGroup"
},
{
"schemaKey":
"PropertyValue",
"value":
"BehavioralEvents"
},
{
"schemaKey":
"PropertyValue",
"value":
"ProcessingModule"
}
],
"wasAttributedTo":
[
{
"age":
{
"schemaKey":
"PropertyValue",
"unitText":
"ISO-8601 duration",
"value":
"P39Y",
"valueReference":
{
"schemaKey":
"PropertyValue",
"value":
"dandi:BirthReference"
}
},
"identifier":
"02",
"schemaKey":
"Participant",
"sex":
{
"identifier":
"http://purl.obolibrary.org/obo/PATO_0000384",
"name":
"Male",
"schemaKey":
"SexType"
},
"species":
{
"identifier":
"http://purl.obolibrary.org/obo/NCBITaxon_9606",
"name":
"Homo sapiens - Human",
"schemaKey":
"SpeciesType"
}
}
],
"wasGeneratedBy":
[
{
"description":
"Running experiment as described in the the experiment description",
"name":
"Acquisition session",
"schemaKey":
"Session",
"startDate":
"2016-02-11T12:06:00+01:00"
},
{
"description":
"Metadata generated by DANDI cli",
"endDate":
"2023-07-04T16:38:10.054341+02:00",
"id":
"urn:uuid:f65143ba-6edb-4c93-ad70-bb60c7ca1a3d",
"name":
"Metadata generation",
"schemaKey":
"Activity",
"startDate":
"2023-07-04T16:38:09.826874+02:00",
"wasAssociatedWith":
[
{
"identifier":
"RRID:SCR_019009",
"name":
"DANDI Command Line Interface",
"schemaKey":
"Software",
"url":
"https://github.com/dandi/dandi-cli",
"version":
"0.55.1"
}
]
}
]
},
"modified":
"2023-07-04T14:58:10.131865+00:00",
"path":
"sub-02/sub-02_ses-20160211T120600_behavior+ecephys.nwb",
"size":
381140617
},
{
"asset_id":
"bfd05b49-680b-41ba-a176-8dcb5b8bbe17",
"blob":
"77e50a2d-6327-41a3-b247-f2df10b93c23",
"created":
"2023-07-04T15:12:13.826352+00:00",
"metadata":
{
"@context":
"https://raw.githubusercontent.com/dandi/schema/master/releases/0.6.4/context.json",
"access":
[
{
"schemaKey":
"AccessRequirements",
"status":
"dandi:OpenAccess"
}
],
"approach":
[
{
"name":
"behavioral approach",
"schemaKey":
"ApproachType"
},
{
"name":
"electrophysiological approach",
"schemaKey":
"ApproachType"
}
],
"blobDateModified":
"2023-07-04T15:10:52.973497+02:00",
"contentSize":
403692571,
"contentUrl":
[
"https://api.dandiarchive.org/api/assets/bfd05b49-680b-41ba-a176-8dcb5b8bbe17/download/",
"https://dandiarchive.s3.amazonaws.com/blobs/77e/50a/77e50a2d-6327-41a3-b247-f2df10b93c23"
],
"dateModified":
"2023-07-04T16:42:02.323671+02:00",
"digest":
{
"dandi:dandi-etag":
"215ef43de4f5aebda1fe9aeece81c419-7",
"dandi:sha2-256":
"23f45b52a303bff90be231da2a0301513b0ec4f10f0e8fb5b41cf2a492b70d95"
},
"encodingFormat":
"application/x-nwb",
"id":
"dandiasset:bfd05b49-680b-41ba-a176-8dcb5b8bbe17",
"identifier":
"bfd05b49-680b-41ba-a176-8dcb5b8bbe17",
"keywords":
[
"Neuroscience",
"Electrophysiology",
"Human",
"Awake",
"Local field potential",
"Neuronal action potential",
"Spikes",
"Medial temporal lobe",
"Hippocampus",
"Entorhinal cortex",
"Amygdala",
"Scalp EEG",
"Intracranial EEG",
"Cognitive task",
"Verbal working memory",
"Epilepsy"
],
"measurementTechnique":
[
{
"name":
"analytical technique",
"schemaKey":
"MeasurementTechniqueType"
},
{
"name":
"signal filtering technique",
"schemaKey":
"MeasurementTechniqueType"
},
{
"name":
"behavioral technique",
"schemaKey":
"MeasurementTechniqueType"
},
{
"name":
"surgical technique",
"schemaKey":
"MeasurementTechniqueType"
},
{
"name":
"spike sorting technique",
"schemaKey":
"MeasurementTechniqueType"
},
{
"name":
"multi electrode extracellular electrophysiology recording technique",
"schemaKey":
"MeasurementTechniqueType"
}
],
"path":
"sub-02/sub-02_ses-20160211T153300_behavior+ecephys.nwb",
"schemaKey":
"Asset",
"schemaVersion":
"0.6.4",
"variableMeasured":
[
{
"schemaKey":
"PropertyValue",
"value":
"Units"
},
{
"schemaKey":
"PropertyValue",
"value":
"LFP"
},
{
"schemaKey":
"PropertyValue",
"value":
"ElectricalSeries"
},
{
"schemaKey":
"PropertyValue",
"value":
"ElectrodeGroup"
},
{
"schemaKey":
"PropertyValue",
"value":
"BehavioralEvents"
},
{
"schemaKey":
"PropertyValue",
"value":
"ProcessingModule"
}
],
"wasAttributedTo":
[
{
"age":
{
"schemaKey":
"PropertyValue",
"unitText":
"ISO-8601 duration",
"value":
"P39Y",
"valueReference":
{
"schemaKey":
"PropertyValue",
"value":
"dandi:BirthReference"
}
},
"identifier":
"02",
"schemaKey":
"Participant",
"sex":
{
"identifier":
"http://purl.obolibrary.org/obo/PATO_0000384",
"name":
"Male",
"schemaKey":
"SexType"
},
"species":
{
"identifier":
"http://purl.obolibrary.org/obo/NCBITaxon_9606",
"name":
"Homo sapiens - Human",
"schemaKey":
"SpeciesType"
}
}
],
"wasGeneratedBy":
[
{
"description":
"Running experiment as described in the the experiment description",
"name":
"Acquisition session",
"schemaKey":
"Session",
"startDate":
"2016-02-11T15:33:00+01:00"
},
{
"description":
"Metadata generated by DANDI cli",
"endDate":
"2023-07-04T16:42:02.323671+02:00",
"id":
"urn:uuid:e36a6751-b0b2-42c2-8f75-94d4e8c302d6",
"name":
"Metadata generation",
"schemaKey":
"Activity",
"startDate":
"2023-07-04T16:42:02.130767+02:00",
"wasAssociatedWith":
[
{
"identifier":
"RRID:SCR_019009",
"name":
"DANDI Command Line Interface",
"schemaKey":
"Software",
"url":
"https://github.com/dandi/dandi-cli",
"version":
"0.55.1"
}
]
}
]
},
"modified":
"2023-07-04T15:12:17.000157+00:00",
"path":
"sub-02/sub-02_ses-20160211T153300_behavior+ecephys.nwb",
"size":
403692571
},
{
"asset_id":
"9fd0f92c-e403-4448-b50b-d481dace1ae3",
"blob":
"0092e7b5-fc91-43fc-89e9-1bc0b88e210b",
"created":
"2023-07-04T15:09:37.655010+00:00",
"metadata":
{
"@context":
"https://raw.githubusercontent.com/dandi/schema/master/releases/0.6.4/context.json",
"access":
[
{
"schemaKey":
"AccessRequirements",
"status":
"dandi:OpenAccess"
}
],
"approach":
[
{
"name":
"behavioral approach",
"schemaKey":
"ApproachType"
},
{
"name":
"electrophysiological approach",
"schemaKey":
"ApproachType"
}
],
"blobDateModified":
"2023-07-04T15:11:26.705195+02:00",
"contentSize":
389235738,
"contentUrl":
[
"https://api.dandiarchive.org/api/assets/9fd0f92c-e403-4448-b50b-d481dace1ae3/download/",
"https://dandiarchive.s3.amazonaws.com/blobs/009/2e7/0092e7b5-fc91-43fc-89e9-1bc0b88e210b"
],
"dateModified":
"2023-07-04T16:46:38.637011+02:00",
"digest":
{
"dandi:dandi-etag":
"bdaee798e50fe44aab817f711efb92f6-6",
"dandi:sha2-256":
"0c8ca29ebc747fb2825bc346caca372841dcbaf6972cf1818c748223ef9e9391"
},
"encodingFormat":
"application/x-nwb",
"id":
"dandiasset:9fd0f92c-e403-4448-b50b-d481dace1ae3",
"identifier":
"9fd0f92c-e403-4448-b50b-d481dace1ae3",
"keywords":
[
"Neuroscience",
"Electrophysiology",
"Human",
"Awake",
"Local field potential",
"Neuronal action potential",
"Spikes",
"Medial temporal lobe",
"Hippocampus",
"Entorhinal cortex",
"Amygdala",
"Scalp EEG",
"Intracranial EEG",
"Cognitive task",
"Verbal working memory",
"Epilepsy"
],
"measurementTechnique":
[
{
"name":
"analytical technique",
"schemaKey":
"MeasurementTechniqueType"
},
{
"name":
"signal filtering technique",
"schemaKey":
"MeasurementTechniqueType"
},
{
"name":
"behavioral technique",
"schemaKey":
"MeasurementTechniqueType"
},
{
"name":
"surgical technique",
"schemaKey":
"MeasurementTechniqueType"
},
{
"name":
"spike sorting technique",
"schemaKey":
"MeasurementTechniqueType"
},
{
"name":
"multi electrode extracellular electrophysiology recording technique",
"schemaKey":
"MeasurementTechniqueType"
}
],
"path":
"sub-02/sub-02_ses-20160212T165900_behavior+ecephys.nwb",
"schemaKey":
"Asset",
"schemaVersion":
"0.6.4",
"variableMeasured":
[
{
"schemaKey":
"PropertyValue",
"value":
"Units"
},
{
"schemaKey":
"PropertyValue",
"value":
"LFP"
},
{
"schemaKey":
"PropertyValue",
"value":
"ElectricalSeries"
},
{
"schemaKey":
"PropertyValue",
"value":
"ElectrodeGroup"
},
{
"schemaKey":
"PropertyValue",
"value":
"BehavioralEvents"
},
{
"schemaKey":
"PropertyValue",
"value":
"ProcessingModule"
}
],
"wasAttributedTo":
[
{
"age":
{
"schemaKey":
"PropertyValue",
"unitText":
"ISO-8601 duration",
"value":
"P39Y",
"valueReference":
{
"schemaKey":
"PropertyValue",
"value":
"dandi:BirthReference"
}
},
"identifier":
"02",
"schemaKey":
"Participant",
"sex":
{
"identifier":
"http://purl.obolibrary.org/obo/PATO_0000384",
"name":
"Male",
"schemaKey":
"SexType"
},
"species":
{
"identifier":
"http://purl.obolibrary.org/obo/NCBITaxon_9606",
"name":
"Homo sapiens - Human",
"schemaKey":
"SpeciesType"
}
}
],
"wasGeneratedBy":
[
{
"description":
"Running experiment as described in the the experiment description",
"name":
"Acquisition session",
"schemaKey":
"Session",
"startDate":
"2016-02-12T16:59:00+01:00"
},
{
"description":
"Metadata generated by DANDI cli",
"endDate":
"2023-07-04T16:46:38.637011+02:00",
"id":
"urn:uuid:a8ab5d83-e09d-474c-99ff-d73bdce35bfc",
"name":
"Metadata generation",
"schemaKey":
"Activity",
"startDate":
"2023-07-04T16:46:38.439950+02:00",
"wasAssociatedWith":
[
{
"identifier":
"RRID:SCR_019009",
"name":
"DANDI Command Line Interface",
"schemaKey":
"Software",
"url":
"https://github.com/dandi/dandi-cli",
"version":
"0.55.1"
}
]
}
]
},
"modified":
"2023-07-04T15:09:39.025201+00:00",
"path":
"sub-02/sub-02_ses-20160212T165900_behavior+ecephys.nwb",
"size":
389235738
},
{
"asset_id":
"fa9abd31-cc8a-4d4f-b8d6-fcb7d4ad49a3",
"blob":
"f8973558-39c4-4aad-996f-3bf07ec93633",
"created":
"2023-07-04T15:09:10.346032+00:00",
"metadata":
{
"@context":
"https://raw.githubusercontent.com/dandi/schema/master/releases/0.6.4/context.json",
"access":
[
{
"schemaKey":
"AccessRequirements",
"status":
"dandi:OpenAccess"
}
],
"approach":
[
{
"name":
"behavioral approach",
"schemaKey":
"ApproachType"
},
{
"name":
"electrophysiological approach",
"schemaKey":
"ApproachType"
}
],
"blobDateModified":
"2023-07-04T15:11:53.149962+02:00",
"contentSize":
372820706,
"contentUrl":
[
"https://api.dandiarchive.org/api/assets/fa9abd31-cc8a-4d4f-b8d6-fcb7d4ad49a3/download/",
"https://dandiarchive.s3.amazonaws.com/blobs/f89/735/f8973558-39c4-4aad-996f-3bf07ec93633"
],
"dateModified":
"2023-07-04T16:47:54.731891+02:00",
"digest":
{
"dandi:dandi-etag":
"339cfe1a86b491c90fc05b97e89cab54-6",
"dandi:sha2-256":
"dc735cb46ea7674df3b3adef16f5aa05ab883b6770254fdd3b37ff9ee8e0994f"
},
"encodingFormat":
"application/x-nwb",
"id":
"dandiasset:fa9abd31-cc8a-4d4f-b8d6-fcb7d4ad49a3",
"identifier":
"fa9abd31-cc8a-4d4f-b8d6-fcb7d4ad49a3",
"keywords":
[
"Neuroscience",
"Electrophysiology",
"Human",
"Awake",
"Local field potential",
"Neuronal action potential",
"Spikes",
"Medial temporal lobe",
"Hippocampus",
"Entorhinal cortex",
"Amygdala",
"Scalp EEG",
"Intracranial EEG",
"Cognitive task",
"Verbal working memory",
"Epilepsy"
],
"measurementTechnique":
[
{
"name":
"analytical technique",
"schemaKey":
"MeasurementTechniqueType"
},
{
"name":
"signal filtering technique",
"schemaKey":
"MeasurementTechniqueType"
},
{
"name":
"behavioral technique",
"schemaKey":
"MeasurementTechniqueType"
},
{
"name":
"surgical technique",
"schemaKey":
"MeasurementTechniqueType"
},
{
"name":
"spike sorting technique",
"schemaKey":
"MeasurementTechniqueType"
},
{
"name":
"multi electrode extracellular electrophysiology recording technique",
"schemaKey":
"MeasurementTechniqueType"
}
],
"path":
"sub-02/sub-02_ses-20160213T153700_obj-1kmymdb_behavior+ecephys.nwb",
"schemaKey":
"Asset",
"schemaVersion":
"0.6.4",
"variableMeasured":
[
{
"schemaKey":
"PropertyValue",
"value":
"Units"
},
{
"schemaKey":
"PropertyValue",
"value":
"LFP"
},
{
"schemaKey":
"PropertyValue",
"value":
"ElectricalSeries"
},
{
"schemaKey":
"PropertyValue",
"value":
"ElectrodeGroup"
},
{
"schemaKey":
"PropertyValue",
"value":
"BehavioralEvents"
},
{
"schemaKey":
"PropertyValue",
"value":
"ProcessingModule"
}
],
"wasAttributedTo":
[
{
"age":
{
"schemaKey":
"PropertyValue",
"unitText":
"ISO-8601 duration",
"value":
"P39Y",
"valueReference":
{
"schemaKey":
"PropertyValue",
"value":
"dandi:BirthReference"
}
},
"identifier":
"02",
"schemaKey":
"Participant",
"sex":
{
"identifier":
"http://purl.obolibrary.org/obo/PATO_0000384",
"name":
"Male",
"schemaKey":
"SexType"
},
"species":
{
"identifier":
"http://purl.obolibrary.org/obo/NCBITaxon_9606",
"name":
"Homo sapiens - Human",
"schemaKey":
"SpeciesType"
}
}
],
"wasGeneratedBy":
[
{
"description":
"Running experiment as described in the the experiment description",
"name":
"Acquisition session",
"schemaKey":
"Session",
"startDate":
"2016-02-13T15:37:00+01:00"
},
{
"description":
"Metadata generated by DANDI cli",
"endDate":
"2023-07-04T16:47:54.731891+02:00",
"id":
"urn:uuid:92f9ccef-7ac4-4404-a27a-27552a94e5e5",
"name":
"Metadata generation",
"schemaKey":
"Activity",
"startDate":
"2023-07-04T16:47:54.518809+02:00",
"wasAssociatedWith":
[
{
"identifier":
"RRID:SCR_019009",
"name":
"DANDI Command Line Interface",
"schemaKey":
"Software",
"url":
"https://github.com/dandi/dandi-cli",
"version":
"0.55.1"
}
]
}
]
},
"modified":
"2023-07-04T15:09:13.004049+00:00",
"path":
"sub-02/sub-02_ses-20160213T153700_obj-1kmymdb_behavior+ecephys.nwb",
"size":
372820706
},
{
"asset_id":
"0e59cfe6-eacc-4fe2-99bd-fb4ff74772f3",
"blob":
"ab706e33-8d2b-434d-acf1-d97dd87101c7",
"created":
"2023-07-04T15:14:58.875509+00:00",
"metadata":
{
"@context":
"https://raw.githubusercontent.com/dandi/schema/master/releases/0.6.4/context.json",
"access":
[
{
"schemaKey":
"AccessRequirements",
"status":
"dandi:OpenAccess"
}
],
"approach":
[
{
"name":
"behavioral approach",
"schemaKey":
"ApproachType"
},
{
"name":
"electrophysiological approach",
"schemaKey":
"ApproachType"
}
],
"blobDateModified":
"2023-07-04T15:12:45.109764+02:00",
"contentSize":
397117294,
"contentUrl":
[
"https://api.dandiarchive.org/api/assets/0e59cfe6-eacc-4fe2-99bd-fb4ff74772f3/download/",
"https://dandiarchive.s3.amazonaws.com/blobs/ab7/06e/ab706e33-8d2b-434d-acf1-d97dd87101c7"
],
"dateModified":
"2023-07-04T16:53:33.554881+02:00",
"digest":
{
"dandi:dandi-etag":
"9702ae1c1330745b925606a310af3922-6",
"dandi:sha2-256":
"a277f70c914d6c15dd5b7e0705b8b74ceb3dd60a062b7da901a5bf30b3feaae2"
},
"encodingFormat":
"application/x-nwb",
"id":
"dandiasset:0e59cfe6-eacc-4fe2-99bd-fb4ff74772f3",
"identifier":
"0e59cfe6-eacc-4fe2-99bd-fb4ff74772f3",
"keywords":
[
"Neuroscience",
"Electrophysiology",
"Human",
"Awake",
"Local field potential",
"Neuronal action potential",
"Spikes",
"Medial temporal lobe",
"Hippocampus",
"Entorhinal cortex",
"Amygdala",
"Scalp EEG",
"Intracranial EEG",
"Cognitive task",
"Verbal working memory",
"Epilepsy"
],
"measurementTechnique":
[
{
"name":
"analytical technique",
"schemaKey":
"MeasurementTechniqueType"
},
{
"name":
"signal filtering technique",
"schemaKey":
"MeasurementTechniqueType"
},
{
"name":
"behavioral technique",
"schemaKey":
"MeasurementTechniqueType"
},
{
"name":
"surgical technique",
"schemaKey":
"MeasurementTechniqueType"
},
{
"name":
"spike sorting technique",
"schemaKey":
"MeasurementTechniqueType"
},
{
"name":
"multi electrode extracellular electrophysiology recording technique",
"schemaKey":
"MeasurementTechniqueType"
}
],
"path":
"sub-02/sub-02_ses-20160213T153700_obj-1q6k4uj_behavior+ecephys.nwb",
"schemaKey":
"Asset",
"schemaVersion":
"0.6.4",
"variableMeasured":
[
{
"schemaKey":
"PropertyValue",
"value":
"Units"
},
{
"schemaKey":
"PropertyValue",
"value":
"LFP"
},
{
"schemaKey":
"PropertyValue",
"value":
"ElectricalSeries"
},
{
"schemaKey":
"PropertyValue",
"value":
"ElectrodeGroup"
},
{
"schemaKey":
"PropertyValue",
"value":
"BehavioralEvents"
},
{
"schemaKey":
"PropertyValue",
"value":
"ProcessingModule"
}
],
"wasAttributedTo":
[
{
"age":
{
"schemaKey":
"PropertyValue",
"unitText":
"ISO-8601 duration",
"value":
"P39Y",
"valueReference":
{
"schemaKey":
"PropertyValue",
"value":
"dandi:BirthReference"
}
},
"identifier":
"02",
"schemaKey":
"Participant",
"sex":
{
"identifier":
"http://purl.obolibrary.org/obo/PATO_0000384",
"name":
"Male",
"schemaKey":
"SexType"
},
"species":
{
"identifier":
"http://purl.obolibrary.org/obo/NCBITaxon_9606",
"name":
"Homo sapiens - Human",
"schemaKey":
"SpeciesType"
}
}
],
"wasGeneratedBy":
[
{
"description":
"Running experiment as described in the the experiment description",
"name":
"Acquisition session",
"schemaKey":
"Session",
"startDate":
"2016-02-13T15:37:00+01:00"
},
{
"description":
"Metadata generated by DANDI cli",
"endDate":
"2023-07-04T16:53:33.554881+02:00",
"id":
"urn:uuid:e66b868f-b885-42a7-b96b-039bce07a46e",
"name":
"Metadata generation",
"schemaKey":
"Activity",
"startDate":
"2023-07-04T16:53:33.360155+02:00",
"wasAssociatedWith":
[
{
"identifier":
"RRID:SCR_019009",
"name":
"DANDI Command Line Interface",
"schemaKey":
"Software",
"url":
"https://github.com/dandi/dandi-cli",
"version":
"0.55.1"
}
]
}
]
},
"modified":
"2023-07-04T15:15:03.497103+00:00",
"path":
"sub-02/sub-02_ses-20160213T153700_obj-1q6k4uj_behavior+ecephys.nwb",
"size":
397117294
},
{
"asset_id":
"0a21ad90-0e45-4881-8995-961396a99d31",
"blob":
"26e9094f-e55d-406f-a170-7d2112cea0f0",
"created":
"2023-07-04T15:20:08.856882+00:00",
"metadata":
{
"@context":
"https://raw.githubusercontent.com/dandi/schema/master/releases/0.6.4/context.json",
"access":
[
{
"schemaKey":
"AccessRequirements",
"status":
"dandi:OpenAccess"
}
],
"approach":
[
{
"name":
"behavioral approach",
"schemaKey":
"ApproachType"
},
{
"name":
"electrophysiological approach",
"schemaKey":
"ApproachType"
}
],
"blobDateModified":
"2023-07-04T15:12:19.354800+02:00",
"contentSize":
405167834,
"contentUrl":
[
"https://api.dandiarchive.org/api/assets/0a21ad90-0e45-4881-8995-961396a99d31/download/",
"https://dandiarchive.s3.amazonaws.com/blobs/26e/909/26e9094f-e55d-406f-a170-7d2112cea0f0"
],
"dateModified":
"2023-07-04T16:58:08.933082+02:00",
"digest":
{
"dandi:dandi-etag":
"e33100cd56c8c3d819c123bb57a7ec16-7",
"dandi:sha2-256":
"4b7c725e5a62a14b06d1428e7763ec1571bc6500106c8b33268b24a493aeaad8"
},
"encodingFormat":
"application/x-nwb",
"id":
"dandiasset:0a21ad90-0e45-4881-8995-961396a99d31",
"identifier":
"0a21ad90-0e45-4881-8995-961396a99d31",
"keywords":
[
"Neuroscience",
"Electrophysiology",
"Human",
"Awake",
"Local field potential",
"Neuronal action potential",
"Spikes",
"Medial temporal lobe",
"Hippocampus",
"Entorhinal cortex",
"Amygdala",
"Scalp EEG",
"Intracranial EEG",
"Cognitive task",
"Verbal working memory",
"Epilepsy"
],
"measurementTechnique":
[
{
"name":
"analytical technique",
"schemaKey":
"MeasurementTechniqueType"
},
{
"name":
"signal filtering technique",
"schemaKey":
"MeasurementTechniqueType"
},
{
"name":
"behavioral technique",
"schemaKey":
"MeasurementTechniqueType"
},
{
"name":
"surgical technique",
"schemaKey":
"MeasurementTechniqueType"
},
{
"name":
"spike sorting technique",
"schemaKey":
"MeasurementTechniqueType"
},
{
"name":
"multi electrode extracellular electrophysiology recording technique",
"schemaKey":
"MeasurementTechniqueType"
}
],
"path":
"sub-02/sub-02_ses-20160213T153700_obj-5ekw3l_behavior+ecephys.nwb",
"schemaKey":
"Asset",
"schemaVersion":
"0.6.4",
"variableMeasured":
[
{
"schemaKey":
"PropertyValue",
"value":
"Units"
},
{
"schemaKey":
"PropertyValue",
"value":
"LFP"
},
{
"schemaKey":
"PropertyValue",
"value":
"ElectricalSeries"
},
{
"schemaKey":
"PropertyValue",
"value":
"ElectrodeGroup"
},
{
"schemaKey":
"PropertyValue",
"value":
"BehavioralEvents"
},
{
"schemaKey":
"PropertyValue",
"value":
"ProcessingModule"
}
],
"wasAttributedTo":
[
{
"age":
{
"schemaKey":
"PropertyValue",
"unitText":
"ISO-8601 duration",
"value":
"P39Y",
"valueReference":
{
"schemaKey":
"PropertyValue",
"value":
"dandi:BirthReference"
}
},
"identifier":
"02",
"schemaKey":
"Participant",
"sex":
{
"identifier":
"http://purl.obolibrary.org/obo/PATO_0000384",
"name":
"Male",
"schemaKey":
"SexType"
},
"species":
{
"identifier":
"http://purl.obolibrary.org/obo/NCBITaxon_9606",
"name":
"Homo sapiens - Human",
"schemaKey":
"SpeciesType"
}
}
],
"wasGeneratedBy":
[
{
"description":
"Running experiment as described in the the experiment description",
"name":
"Acquisition session",
"schemaKey":
"Session",
"startDate":
"2016-02-13T15:37:00+01:00"
},
{
"description":
"Metadata generated by DANDI cli",
"endDate":
"2023-07-04T16:58:08.933082+02:00",
"id":
"urn:uuid:71df1971-db76-4081-ac68-46d59f507536",
"name":
"Metadata generation",
"schemaKey":
"Activity",
"startDate":
"2023-07-04T16:58:08.739881+02:00",
"wasAssociatedWith":
[
{
"identifier":
"RRID:SCR_019009",
"name":
"DANDI Command Line Interface",
"schemaKey":
"Software",
"url":
"https://github.com/dandi/dandi-cli",
"version":
"0.55.1"
}
]
}
]
},
"modified":
"2023-07-04T15:20:11.409338+00:00",
"path":
"sub-02/sub-02_ses-20160213T153700_obj-5ekw3l_behavior+ecephys.nwb",
"size":
405167834
},
{
"asset_id":
"0b2cf359-118c-4352-b477-8c3b7caee815",
"blob":
"7d582989-0e51-4f78-a54e-b1cb169ff67a",
"created":
"2023-07-04T15:21:00.697922+00:00",
"metadata":
{
"@context":
"https://raw.githubusercontent.com/dandi/schema/master/releases/0.6.4/context.json",
"access":
[
{
"schemaKey":
"AccessRequirements",
"status":
"dandi:OpenAccess"
}
],
"approach":
[
{
"name":
"behavioral approach",
"schemaKey":
"ApproachType"
},
{
"name":
"electrophysiological approach",
"schemaKey":
"ApproachType"
}
],
"blobDateModified":
"2023-07-04T15:13:03.270186+02:00",
"contentSize":
242218994,
"contentUrl":
[
"https://api.dandiarchive.org/api/assets/0b2cf359-118c-4352-b477-8c3b7caee815/download/",
"https://dandiarchive.s3.amazonaws.com/blobs/7d5/829/7d582989-0e51-4f78-a54e-b1cb169ff67a"
],
"dateModified":
"2023-07-04T17:09:11.933505+02:00",
"digest":
{
"dandi:dandi-etag":
"415b342e3d850ee25acb50fb9592dbb4-4",
"dandi:sha2-256":
"ff126cc2304ef90d2682d721f6bada6c07b124922a74084e380548a139ca512d"
},
"encodingFormat":
"application/x-nwb",
"id":
"dandiasset:0b2cf359-118c-4352-b477-8c3b7caee815",
"identifier":
"0b2cf359-118c-4352-b477-8c3b7caee815",
"keywords":
[
"Neuroscience",
"Electrophysiology",
"Human",
"Awake",
"Local field potential",
"Neuronal action potential",
"Spikes",
"Medial temporal lobe",
"Hippocampus",
"Entorhinal cortex",
"Amygdala",
"Scalp EEG",
"Intracranial EEG",
"Cognitive task",
"Verbal working memory",
"Epilepsy"
],
"measurementTechnique":
[
{
"name":
"analytical technique",
"schemaKey":
"MeasurementTechniqueType"
},
{
"name":
"signal filtering technique",
"schemaKey":
"MeasurementTechniqueType"
},
{
"name":
"behavioral technique",
"schemaKey":
"MeasurementTechniqueType"
},
{
"name":
"surgical technique",
"schemaKey":
"MeasurementTechniqueType"
},
{
"name":
"spike sorting technique",
"schemaKey":
"MeasurementTechniqueType"
},
{
"name":
"multi electrode extracellular electrophysiology recording technique",
"schemaKey":
"MeasurementTechniqueType"
}
],
"path":
"sub-03/sub-03_ses-20150304T165900_behavior+ecephys.nwb",
"schemaKey":
"Asset",
"schemaVersion":
"0.6.4",
"variableMeasured":
[
{
"schemaKey":
"PropertyValue",
"value":
"Units"
},
{
"schemaKey":
"PropertyValue",
"value":
"LFP"
},
{
"schemaKey":
"PropertyValue",
"value":
"ElectricalSeries"
},
{
"schemaKey":
"PropertyValue",
"value":
"ElectrodeGroup"
},
{
"schemaKey":
"PropertyValue",
"value":
"BehavioralEvents"
},
{
"schemaKey":
"PropertyValue",
"value":
"ProcessingModule"
}
],
"wasAttributedTo":
[
{
"age":
{
"schemaKey":
"PropertyValue",
"unitText":
"ISO-8601 duration",
"value":
"P18Y",
"valueReference":
{
"schemaKey":
"PropertyValue",
"value":
"dandi:BirthReference"
}
},
"identifier":
"03",
"schemaKey":
"Participant",
"sex":
{
"identifier":
"http://purl.obolibrary.org/obo/PATO_0000383",
"name":
"Female",
"schemaKey":
"SexType"
},
"species":
{
"identifier":
"http://purl.obolibrary.org/obo/NCBITaxon_9606",
"name":
"Homo sapiens - Human",
"schemaKey":
"SpeciesType"
}
}
],
"wasGeneratedBy":
[
{
"description":
"Running experiment as described in the the experiment description",
"name":
"Acquisition session",
"schemaKey":
"Session",
"startDate":
"2015-03-04T16:59:00+01:00"
},
{
"description":
"Metadata generated by DANDI cli",
"endDate":
"2023-07-04T17:09:11.933505+02:00",
"id":
"urn:uuid:6e824c84-39d6-4207-9175-89801f8e3891",
"name":
"Metadata generation",
"schemaKey":
"Activity",
"startDate":
"2023-07-04T17:09:11.749644+02:00",
"wasAssociatedWith":
[
{
"identifier":
"RRID:SCR_019009",
"name":
"DANDI Command Line Interface",
"schemaKey":
"Software",
"url":
"https://github.com/dandi/dandi-cli",
"version":
"0.55.1"
}
]
}
]
},
"modified":
"2023-07-04T15:21:02.636490+00:00",
"path":
"sub-03/sub-03_ses-20150304T165900_behavior+ecephys.nwb",
"size":
242218994
},
{
"asset_id":
"05ec2d61-d0d8-4f36-9a08-ec59cc5dae21",
"blob":
"346b0c58-784a-4570-8fd3-48e966d2e204",
"created":
"2023-07-04T15:21:41.837589+00:00",
"metadata":
{
"@context":
"https://raw.githubusercontent.com/dandi/schema/master/releases/0.6.4/context.json",
"access":
[
{
"schemaKey":
"AccessRequirements",
"status":
"dandi:OpenAccess"
}
],
"approach":
[
{
"name":
"behavioral approach",
"schemaKey":
"ApproachType"
},
{
"name":
"electrophysiological approach",
"schemaKey":
"ApproachType"
}
],
"blobDateModified":
"2023-07-04T15:13:22.488198+02:00",
"contentSize":
257926741,
"contentUrl":
[
"https://api.dandiarchive.org/api/assets/05ec2d61-d0d8-4f36-9a08-ec59cc5dae21/download/",
"https://dandiarchive.s3.amazonaws.com/blobs/346/b0c/346b0c58-784a-4570-8fd3-48e966d2e204"
],
"dateModified":
"2023-07-04T17:09:39.061156+02:00",
"digest":
{
"dandi:dandi-etag":
"0b9d821944bebc3718619141971dbc4f-4",
"dandi:sha2-256":
"9518e886bc97b9a110b1cfda993dbc89cb3d8e145977d9db7461a74b05314db7"
},
"encodingFormat":
"application/x-nwb",
"id":
"dandiasset:05ec2d61-d0d8-4f36-9a08-ec59cc5dae21",
"identifier":
"05ec2d61-d0d8-4f36-9a08-ec59cc5dae21",
"keywords":
[
"Neuroscience",
"Electrophysiology",
"Human",
"Awake",
"Local field potential",
"Neuronal action potential",
"Spikes",
"Medial temporal lobe",
"Hippocampus",
"Entorhinal cortex",
"Amygdala",
"Scalp EEG",
"Intracranial EEG",
"Cognitive task",
"Verbal working memory",
"Epilepsy"
],
"measurementTechnique":
[
{
"name":
"analytical technique",
"schemaKey":
"MeasurementTechniqueType"
},
{
"name":
"signal filtering technique",
"schemaKey":
"MeasurementTechniqueType"
},
{
"name":
"behavioral technique",
"schemaKey":
"MeasurementTechniqueType"
},
{
"name":
"surgical technique",
"schemaKey":
"MeasurementTechniqueType"
},
{
"name":
"spike sorting technique",
"schemaKey":
"MeasurementTechniqueType"
},
{
"name":
"multi electrode extracellular electrophysiology recording technique",
"schemaKey":
"MeasurementTechniqueType"
}
],
"path":
"sub-03/sub-03_ses-20150305T085500_behavior+ecephys.nwb",
"schemaKey":
"Asset",
"schemaVersion":
"0.6.4",
"variableMeasured":
[
{
"schemaKey":
"PropertyValue",
"value":
"Units"
},
{
"schemaKey":
"PropertyValue",
"value":
"LFP"
},
{
"schemaKey":
"PropertyValue",
"value":
"ElectricalSeries"
},
{
"schemaKey":
"PropertyValue",
"value":
"ElectrodeGroup"
},
{
"schemaKey":
"PropertyValue",
"value":
"BehavioralEvents"
},
{
"schemaKey":
"PropertyValue",
"value":
"ProcessingModule"
}
],
"wasAttributedTo":
[
{
"age":
{
"schemaKey":
"PropertyValue",
"unitText":
"ISO-8601 duration",
"value":
"P18Y",
"valueReference":
{
"schemaKey":
"PropertyValue",
"value":
"dandi:BirthReference"
}
},
"identifier":
"03",
"schemaKey":
"Participant",
"sex":
{
"identifier":
"http://purl.obolibrary.org/obo/PATO_0000383",
"name":
"Female",
"schemaKey":
"SexType"
},
"species":
{
"identifier":
"http://purl.obolibrary.org/obo/NCBITaxon_9606",
"name":
"Homo sapiens - Human",
"schemaKey":
"SpeciesType"
}
}
],
"wasGeneratedBy":
[
{
"description":
"Running experiment as described in the the experiment description",
"name":
"Acquisition session",
"schemaKey":
"Session",
"startDate":
"2015-03-05T08:55:00+01:00"
},
{
"description":
"Metadata generated by DANDI cli",
"endDate":
"2023-07-04T17:09:39.061156+02:00",
"id":
"urn:uuid:0b08cda7-0481-46e1-9c8d-433ba4d9df0e",
"name":
"Metadata generation",
"schemaKey":
"Activity",
"startDate":
"2023-07-04T17:09:38.874991+02:00",
"wasAssociatedWith":
[
{
"identifier":
"RRID:SCR_019009",
"name":
"DANDI Command Line Interface",
"schemaKey":
"Software",
"url":
"https://github.com/dandi/dandi-cli",
"version":
"0.55.1"
}
]
}
]
},
"modified":
"2023-07-04T15:21:43.218037+00:00",
"path":
"sub-03/sub-03_ses-20150305T085500_behavior+ecephys.nwb",
"size":
257926741
},
{
"asset_id":
"0fdc15c3-2506-4d50-a5c6-97346095674f",
"blob":
"ebc7bf66-8489-4b05-93ff-1121507ba123",
"created":
"2023-07-04T15:33:27.154814+00:00",
"metadata":
{
"@context":
"https://raw.githubusercontent.com/dandi/schema/master/releases/0.6.4/context.json",
"access":
[
{
"schemaKey":
"AccessRequirements",
"status":
"dandi:OpenAccess"
}
],
"approach":
[
{
"name":
"behavioral approach",
"schemaKey":
"ApproachType"
},
{
"name":
"electrophysiological approach",
"schemaKey":
"ApproachType"
}
],
"blobDateModified":
"2023-07-04T15:13:42.276920+02:00",
"contentSize":
258048062,
"contentUrl":
[
"https://api.dandiarchive.org/api/assets/0fdc15c3-2506-4d50-a5c6-97346095674f/download/",
"https://dandiarchive.s3.amazonaws.com/blobs/ebc/7bf/ebc7bf66-8489-4b05-93ff-1121507ba123"
],
"dateModified":
"2023-07-04T17:12:15.185746+02:00",
"digest":
{
"dandi:dandi-etag":
"f60cce9d8e95e7414b0e2a36427b248c-4",
"dandi:sha2-256":
"216f0528c35d656396ac8d2c5f401b207668235f396acf31584d32aa185a374c"
},
"encodingFormat":
"application/x-nwb",
"id":
"dandiasset:0fdc15c3-2506-4d50-a5c6-97346095674f",
"identifier":
"0fdc15c3-2506-4d50-a5c6-97346095674f",
"keywords":
[
"Neuroscience",
"Electrophysiology",
"Human",
"Awake",
"Local field potential",
"Neuronal action potential",
"Spikes",
"Medial temporal lobe",
"Hippocampus",
"Entorhinal cortex",
"Amygdala",
"Scalp EEG",
"Intracranial EEG",
"Cognitive task",
"Verbal working memory",
"Epilepsy"
],
"measurementTechnique":
[
{
"name":
"analytical technique",
"schemaKey":
"MeasurementTechniqueType"
},
{
"name":
"signal filtering technique",
"schemaKey":
"MeasurementTechniqueType"
},
{
"name":
"behavioral technique",
"schemaKey":
"MeasurementTechniqueType"
},
{
"name":
"surgical technique",
"schemaKey":
"MeasurementTechniqueType"
},
{
"name":
"spike sorting technique",
"schemaKey":
"MeasurementTechniqueType"
},
{
"name":
"multi electrode extracellular electrophysiology recording technique",
"schemaKey":
"MeasurementTechniqueType"
}
],
"path":
"sub-03/sub-03_ses-20150306T173300_behavior+ecephys.nwb",
"schemaKey":
"Asset",
"schemaVersion":
"0.6.4",
"variableMeasured":
[
{
"schemaKey":
"PropertyValue",
"value":
"Units"
},
{
"schemaKey":
"PropertyValue",
"value":
"LFP"
},
{
"schemaKey":
"PropertyValue",
"value":
"ElectricalSeries"
},
{
"schemaKey":
"PropertyValue",
"value":
"ElectrodeGroup"
},
{
"schemaKey":
"PropertyValue",
"value":
"BehavioralEvents"
},
{
"schemaKey":
"PropertyValue",
"value":
"ProcessingModule"
}
],
"wasAttributedTo":
[
{
"age":
{
"schemaKey":
"PropertyValue",
"unitText":
"ISO-8601 duration",
"value":
"P18Y",
"valueReference":
{
"schemaKey":
"PropertyValue",
"value":
"dandi:BirthReference"
}
},
"identifier":
"03",
"schemaKey":
"Participant",
"sex":
{
"identifier":
"http://purl.obolibrary.org/obo/PATO_0000383",
"name":
"Female",
"schemaKey":
"SexType"
},
"species":
{
"identifier":
"http://purl.obolibrary.org/obo/NCBITaxon_9606",
"name":
"Homo sapiens - Human",
"schemaKey":
"SpeciesType"
}
}
],
"wasGeneratedBy":
[
{
"description":
"Running experiment as described in the the experiment description",
"name":
"Acquisition session",
"schemaKey":
"Session",
"startDate":
"2015-03-06T17:33:00+01:00"
},
{
"description":
"Metadata generated by DANDI cli",
"endDate":
"2023-07-04T17:12:15.185746+02:00",
"id":
"urn:uuid:2fe446b8-a168-4a10-8dcd-406a3931e5cf",
"name":
"Metadata generation",
"schemaKey":
"Activity",
"startDate":
"2023-07-04T17:12:14.998081+02:00",
"wasAssociatedWith":
[
{
"identifier":
"RRID:SCR_019009",
"name":
"DANDI Command Line Interface",
"schemaKey":
"Software",
"url":
"https://github.com/dandi/dandi-cli",
"version":
"0.55.1"
}
]
}
]
},
"modified":
"2023-07-04T15:33:29.557582+00:00",
"path":
"sub-03/sub-03_ses-20150306T173300_behavior+ecephys.nwb",
"size":
258048062
},
{
"asset_id":
"d9406178-151a-49a3-b413-9ba0c93308d4",
"blob":
"3f44dfe0-4b4b-41c2-8a3d-90922b547637",
"created":
"2023-07-04T15:37:32.952630+00:00",
"metadata":
{
"@context":
"https://raw.githubusercontent.com/dandi/schema/master/releases/0.6.4/context.json",
"access":
[
{
"schemaKey":
"AccessRequirements",
"status":
"dandi:OpenAccess"
}
],
"approach":
[
{
"name":
"behavioral approach",
"schemaKey":
"ApproachType"
},
{
"name":
"electrophysiological approach",
"schemaKey":
"ApproachType"
}
],
"blobDateModified":
"2023-07-04T15:14:20.625642+02:00",
"contentSize":
404907048,
"contentUrl":
[
"https://api.dandiarchive.org/api/assets/d9406178-151a-49a3-b413-9ba0c93308d4/download/",
"https://dandiarchive.s3.amazonaws.com/blobs/3f4/4df/3f44dfe0-4b4b-41c2-8a3d-90922b547637"
],
"dateModified":
"2023-07-04T17:15:00.803220+02:00",
"digest":
{
"dandi:dandi-etag":
"2fd6897d54e672a61e776952207627eb-7",
"dandi:sha2-256":
"413cd8f7fcf2c8d0ab09821609cef4e2415ae15325918a3282a64659574678c7"
},
"encodingFormat":
"application/x-nwb",
"id":
"dandiasset:d9406178-151a-49a3-b413-9ba0c93308d4",
"identifier":
"d9406178-151a-49a3-b413-9ba0c93308d4",
"keywords":
[
"Neuroscience",
"Electrophysiology",
"Human",
"Awake",
"Local field potential",
"Neuronal action potential",
"Spikes",
"Medial temporal lobe",
"Hippocampus",
"Entorhinal cortex",
"Amygdala",
"Scalp EEG",
"Intracranial EEG",
"Cognitive task",
"Verbal working memory",
"Epilepsy"
],
"measurementTechnique":
[
{
"name":
"analytical technique",
"schemaKey":
"MeasurementTechniqueType"
},
{
"name":
"signal filtering technique",
"schemaKey":
"MeasurementTechniqueType"
},
{
"name":
"behavioral technique",
"schemaKey":
"MeasurementTechniqueType"
},
{
"name":
"surgical technique",
"schemaKey":
"MeasurementTechniqueType"
},
{
"name":
"spike sorting technique",
"schemaKey":
"MeasurementTechniqueType"
},
{
"name":
"multi electrode extracellular electrophysiology recording technique",
"schemaKey":
"MeasurementTechniqueType"
}
],
"path":
"sub-04/sub-04_ses-20170118T103700_behavior+ecephys.nwb",
"schemaKey":
"Asset",
"schemaVersion":
"0.6.4",
"variableMeasured":
[
{
"schemaKey":
"PropertyValue",
"value":
"Units"
},
{
"schemaKey":
"PropertyValue",
"value":
"LFP"
},
{
"schemaKey":
"PropertyValue",
"value":
"ElectricalSeries"
},
{
"schemaKey":
"PropertyValue",
"value":
"ElectrodeGroup"
},
{
"schemaKey":
"PropertyValue",
"value":
"BehavioralEvents"
},
{
"schemaKey":
"PropertyValue",
"value":
"ProcessingModule"
}
],
"wasAttributedTo":
[
{
"age":
{
"schemaKey":
"PropertyValue",
"unitText":
"ISO-8601 duration",
"value":
"P28Y",
"valueReference":
{
"schemaKey":
"PropertyValue",
"value":
"dandi:BirthReference"
}
},
"identifier":
"04",
"schemaKey":
"Participant",
"sex":
{
"identifier":
"http://purl.obolibrary.org/obo/PATO_0000384",
"name":
"Male",
"schemaKey":
"SexType"
},
"species":
{
"identifier":
"http://purl.obolibrary.org/obo/NCBITaxon_9606",
"name":
"Homo sapiens - Human",
"schemaKey":
"SpeciesType"
}
}
],
"wasGeneratedBy":
[
{
"description":
"Running experiment as described in the the experiment description",
"name":
"Acquisition session",
"schemaKey":
"Session",
"startDate":
"2017-01-18T10:37:00+01:00"
},
{
"description":
"Metadata generated by DANDI cli",
"endDate":
"2023-07-04T17:15:00.803220+02:00",
"id":
"urn:uuid:a14b8543-0524-4a3b-b84f-9ca8e0b58b12",
"name":
"Metadata generation",
"schemaKey":
"Activity",
"startDate":
"2023-07-04T17:15:00.604453+02:00",
"wasAssociatedWith":
[
{
"identifier":
"RRID:SCR_019009",
"name":
"DANDI Command Line Interface",
"schemaKey":
"Software",
"url":
"https://github.com/dandi/dandi-cli",
"version":
"0.55.1"
}
]
}
]
},
"modified":
"2023-07-04T15:37:36.124187+00:00",
"path":
"sub-04/sub-04_ses-20170118T103700_behavior+ecephys.nwb",
"size":
404907048
},
{
"asset_id":
"5d381a55-d10c-476b-bbb5-e34d49e95a9d",
"blob":
"1468b22e-9604-488d-858f-2408a073acfe",
"created":
"2023-07-04T15:44:41.506523+00:00",
"metadata":
{
"@context":
"https://raw.githubusercontent.com/dandi/schema/master/releases/0.6.4/context.json",
"access":
[
{
"schemaKey":
"AccessRequirements",
"status":
"dandi:OpenAccess"
}
],
"approach":
[
{
"name":
"behavioral approach",
"schemaKey":
"ApproachType"
},
{
"name":
"electrophysiological approach",
"schemaKey":
"ApproachType"
}
],
"blobDateModified":
"2023-07-04T15:15:01.995646+02:00",
"contentSize":
413158798,
"contentUrl":
[
"https://api.dandiarchive.org/api/assets/5d381a55-d10c-476b-bbb5-e34d49e95a9d/download/",
"https://dandiarchive.s3.amazonaws.com/blobs/146/8b2/1468b22e-9604-488d-858f-2408a073acfe"
],
"dateModified":
"2023-07-04T17:20:10.816585+02:00",
"digest":
{
"dandi:dandi-etag":
"02901968a8e0ec83d4f0f7d097db40ff-7",
"dandi:sha2-256":
"8648cad2848fdc2fa1321749122fe5de41a00b3b88c20d522be12d8137b67d5c"
},
"encodingFormat":
"application/x-nwb",
"id":
"dandiasset:5d381a55-d10c-476b-bbb5-e34d49e95a9d",
"identifier":
"5d381a55-d10c-476b-bbb5-e34d49e95a9d",
"keywords":
[
"Neuroscience",
"Electrophysiology",
"Human",
"Awake",
"Local field potential",
"Neuronal action potential",
"Spikes",
"Medial temporal lobe",
"Hippocampus",
"Entorhinal cortex",
"Amygdala",
"Scalp EEG",
"Intracranial EEG",
"Cognitive task",
"Verbal working memory",
"Epilepsy"
],
"measurementTechnique":
[
{
"name":
"analytical technique",
"schemaKey":
"MeasurementTechniqueType"
},
{
"name":
"signal filtering technique",
"schemaKey":
"MeasurementTechniqueType"
},
{
"name":
"behavioral technique",
"schemaKey":
"MeasurementTechniqueType"
},
{
"name":
"surgical technique",
"schemaKey":
"MeasurementTechniqueType"
},
{
"name":
"spike sorting technique",
"schemaKey":
"MeasurementTechniqueType"
},
{
"name":
"multi electrode extracellular electrophysiology recording technique",
"schemaKey":
"MeasurementTechniqueType"
}
],
"path":
"sub-04/sub-04_ses-20170118T104700_behavior+ecephys.nwb",
"schemaKey":
"Asset",
"schemaVersion":
"0.6.4",
"variableMeasured":
[
{
"schemaKey":
"PropertyValue",
"value":
"Units"
},
{
"schemaKey":
"PropertyValue",
"value":
"LFP"
},
{
"schemaKey":
"PropertyValue",
"value":
"ElectricalSeries"
},
{
"schemaKey":
"PropertyValue",
"value":
"ElectrodeGroup"
},
{
"schemaKey":
"PropertyValue",
"value":
"BehavioralEvents"
},
{
"schemaKey":
"PropertyValue",
"value":
"ProcessingModule"
}
],
"wasAttributedTo":
[
{
"age":
{
"schemaKey":
"PropertyValue",
"unitText":
"ISO-8601 duration",
"value":
"P28Y",
"valueReference":
{
"schemaKey":
"PropertyValue",
"value":
"dandi:BirthReference"
}
},
"identifier":
"04",
"schemaKey":
"Participant",
"sex":
{
"identifier":
"http://purl.obolibrary.org/obo/PATO_0000384",
"name":
"Male",
"schemaKey":
"SexType"
},
"species":
{
"identifier":
"http://purl.obolibrary.org/obo/NCBITaxon_9606",
"name":
"Homo sapiens - Human",
"schemaKey":
"SpeciesType"
}
}
],
"wasGeneratedBy":
[
{
"description":
"Running experiment as described in the the experiment description",
"name":
"Acquisition session",
"schemaKey":
"Session",
"startDate":
"2017-01-18T10:47:00+01:00"
},
{
"description":
"Metadata generated by DANDI cli",
"endDate":
"2023-07-04T17:20:10.816585+02:00",
"id":
"urn:uuid:5cc06b7f-15ae-49cb-a0ed-4de6de333868",
"name":
"Metadata generation",
"schemaKey":
"Activity",
"startDate":
"2023-07-04T17:20:10.623337+02:00",
"wasAssociatedWith":
[
{
"identifier":
"RRID:SCR_019009",
"name":
"DANDI Command Line Interface",
"schemaKey":
"Software",
"url":
"https://github.com/dandi/dandi-cli",
"version":
"0.55.1"
}
]
}
]
},
"modified":
"2023-07-04T15:44:44.245494+00:00",
"path":
"sub-04/sub-04_ses-20170118T104700_behavior+ecephys.nwb",
"size":
413158798
},
{
"asset_id":
"5f0a4b30-2efc-416f-8e4b-e1dc5e240e81",
"blob":
"5a23be2d-6156-4fca-9699-a2191f8abc0f",
"created":
"2023-07-04T15:39:41.797789+00:00",
"metadata":
{
"@context":
"https://raw.githubusercontent.com/dandi/schema/master/releases/0.6.4/context.json",
"access":
[
{
"schemaKey":
"AccessRequirements",
"status":
"dandi:OpenAccess"
}
],
"approach":
[
{
"name":
"behavioral approach",
"schemaKey":
"ApproachType"
},
{
"name":
"electrophysiological approach",
"schemaKey":
"ApproachType"
}
],
"blobDateModified":
"2023-07-04T15:15:24.172290+02:00",
"contentSize":
216079812,
"contentUrl":
[
"https://api.dandiarchive.org/api/assets/5f0a4b30-2efc-416f-8e4b-e1dc5e240e81/download/",
"https://dandiarchive.s3.amazonaws.com/blobs/5a2/3be/5a23be2d-6156-4fca-9699-a2191f8abc0f"
],
"dateModified":
"2023-07-04T17:21:02.413883+02:00",
"digest":
{
"dandi:dandi-etag":
"9faa7b2da48268a353e403a505dd1859-4",
"dandi:sha2-256":
"00336fa695d9a6e3cea90548bb5d46751bb45048f01686ea7827321d88c41c15"
},
"encodingFormat":
"application/x-nwb",
"id":
"dandiasset:5f0a4b30-2efc-416f-8e4b-e1dc5e240e81",
"identifier":
"5f0a4b30-2efc-416f-8e4b-e1dc5e240e81",
"keywords":
[
"Neuroscience",
"Electrophysiology",
"Human",
"Awake",
"Local field potential",
"Neuronal action potential",
"Spikes",
"Medial temporal lobe",
"Hippocampus",
"Entorhinal cortex",
"Amygdala",
"Scalp EEG",
"Intracranial EEG",
"Cognitive task",
"Verbal working memory",
"Epilepsy"
],
"measurementTechnique":
[
{
"name":
"analytical technique",
"schemaKey":
"MeasurementTechniqueType"
},
{
"name":
"signal filtering technique",
"schemaKey":
"MeasurementTechniqueType"
},
{
"name":
"behavioral technique",
"schemaKey":
"MeasurementTechniqueType"
},
{
"name":
"surgical technique",
"schemaKey":
"MeasurementTechniqueType"
},
{
"name":
"spike sorting technique",
"schemaKey":
"MeasurementTechniqueType"
},
{
"name":
"multi electrode extracellular electrophysiology recording technique",
"schemaKey":
"MeasurementTechniqueType"
}
],
"path":
"sub-05/sub-05_ses-20170706T115300_obj-1ophyw1_behavior+ecephys.nwb",
"schemaKey":
"Asset",
"schemaVersion":
"0.6.4",
"variableMeasured":
[
{
"schemaKey":
"PropertyValue",
"value":
"Units"
},
{
"schemaKey":
"PropertyValue",
"value":
"LFP"
},
{
"schemaKey":
"PropertyValue",
"value":
"ElectricalSeries"
},
{
"schemaKey":
"PropertyValue",
"value":
"ElectrodeGroup"
},
{
"schemaKey":
"PropertyValue",
"value":
"BehavioralEvents"
},
{
"schemaKey":
"PropertyValue",
"value":
"ProcessingModule"
}
],
"wasAttributedTo":
[
{
"age":
{
"schemaKey":
"PropertyValue",
"unitText":
"ISO-8601 duration",
"value":
"P20Y",
"valueReference":
{
"schemaKey":
"PropertyValue",
"value":
"dandi:BirthReference"
}
},
"identifier":
"05",
"schemaKey":
"Participant",
"sex":
{
"identifier":
"http://purl.obolibrary.org/obo/PATO_0000383",
"name":
"Female",
"schemaKey":
"SexType"
},
"species":
{
"identifier":
"http://purl.obolibrary.org/obo/NCBITaxon_9606",
"name":
"Homo sapiens - Human",
"schemaKey":
"SpeciesType"
}
}
],
"wasGeneratedBy":
[
{
"description":
"Running experiment as described in the the experiment description",
"name":
"Acquisition session",
"schemaKey":
"Session",
"startDate":
"2017-07-06T11:53:00+02:00"
},
{
"description":
"Metadata generated by DANDI cli",
"endDate":
"2023-07-04T17:21:02.413883+02:00",
"id":
"urn:uuid:57f484ed-dde7-4518-b164-f21724e2586c",
"name":
"Metadata generation",
"schemaKey":
"Activity",
"startDate":
"2023-07-04T17:21:02.138849+02:00",
"wasAssociatedWith":
[
{
"identifier":
"RRID:SCR_019009",
"name":
"DANDI Command Line Interface",
"schemaKey":
"Software",
"url":
"https://github.com/dandi/dandi-cli",
"version":
"0.55.1"
}
]
}
]
},
"modified":
"2023-07-04T15:39:44.724101+00:00",
"path":
"sub-05/sub-05_ses-20170706T115300_obj-1ophyw1_behavior+ecephys.nwb",
"size":
216079812
},
{
"asset_id":
"94343e49-3ed9-425b-89b2-4359afba6cad",
"blob":
"de487800-a2bb-45e9-8d16-bc190835e33a",
"created":
"2023-07-04T15:33:28.686867+00:00",
"metadata":
{
"@context":
"https://raw.githubusercontent.com/dandi/schema/master/releases/0.6.4/context.json",
"access":
[
{
"schemaKey":
"AccessRequirements",
"status":
"dandi:OpenAccess"
}
],
"approach":
[
{
"name":
"behavioral approach",
"schemaKey":
"ApproachType"
},
{
"name":
"electrophysiological approach",
"schemaKey":
"ApproachType"
}
],
"blobDateModified":
"2023-07-04T15:15:47.292232+02:00",
"contentSize":
216123507,
"contentUrl":
[
"https://api.dandiarchive.org/api/assets/94343e49-3ed9-425b-89b2-4359afba6cad/download/",
"https://dandiarchive.s3.amazonaws.com/blobs/de4/878/de487800-a2bb-45e9-8d16-bc190835e33a"
],
"dateModified":
"2023-07-04T17:21:43.098615+02:00",
"digest":
{
"dandi:dandi-etag":
"44bc6ac7e37ba73761698d3fb3acc738-4",
"dandi:sha2-256":
"76b4469aa60667b77954a6a6cb9d642cd95f3d3db53b55ceae6fa85a3d73e29c"
},
"encodingFormat":
"application/x-nwb",
"id":
"dandiasset:94343e49-3ed9-425b-89b2-4359afba6cad",
"identifier":
"94343e49-3ed9-425b-89b2-4359afba6cad",
"keywords":
[
"Neuroscience",
"Electrophysiology",
"Human",
"Awake",
"Local field potential",
"Neuronal action potential",
"Spikes",
"Medial temporal lobe",
"Hippocampus",
"Entorhinal cortex",
"Amygdala",
"Scalp EEG",
"Intracranial EEG",
"Cognitive task",
"Verbal working memory",
"Epilepsy"
],
"measurementTechnique":
[
{
"name":
"analytical technique",
"schemaKey":
"MeasurementTechniqueType"
},
{
"name":
"signal filtering technique",
"schemaKey":
"MeasurementTechniqueType"
},
{
"name":
"behavioral technique",
"schemaKey":
"MeasurementTechniqueType"
},
{
"name":
"surgical technique",
"schemaKey":
"MeasurementTechniqueType"
},
{
"name":
"spike sorting technique",
"schemaKey":
"MeasurementTechniqueType"
},
{
"name":
"multi electrode extracellular electrophysiology recording technique",
"schemaKey":
"MeasurementTechniqueType"
}
],
"path":
"sub-05/sub-05_ses-20170706T115300_obj-jz2qje_behavior+ecephys.nwb",
"schemaKey":
"Asset",
"schemaVersion":
"0.6.4",
"variableMeasured":
[
{
"schemaKey":
"PropertyValue",
"value":
"Units"
},
{
"schemaKey":
"PropertyValue",
"value":
"LFP"
},
{
"schemaKey":
"PropertyValue",
"value":
"ElectricalSeries"
},
{
"schemaKey":
"PropertyValue",
"value":
"ElectrodeGroup"
},
{
"schemaKey":
"PropertyValue",
"value":
"BehavioralEvents"
},
{
"schemaKey":
"PropertyValue",
"value":
"ProcessingModule"
}
],
"wasAttributedTo":
[
{
"age":
{
"schemaKey":
"PropertyValue",
"unitText":
"ISO-8601 duration",
"value":
"P20Y",
"valueReference":
{
"schemaKey":
"PropertyValue",
"value":
"dandi:BirthReference"
}
},
"identifier":
"05",
"schemaKey":
"Participant",
"sex":
{
"identifier":
"http://purl.obolibrary.org/obo/PATO_0000383",
"name":
"Female",
"schemaKey":
"SexType"
},
"species":
{
"identifier":
"http://purl.obolibrary.org/obo/NCBITaxon_9606",
"name":
"Homo sapiens - Human",
"schemaKey":
"SpeciesType"
}
}
],
"wasGeneratedBy":
[
{
"description":
"Running experiment as described in the the experiment description",
"name":
"Acquisition session",
"schemaKey":
"Session",
"startDate":
"2017-07-06T11:53:00+02:00"
},
{
"description":
"Metadata generated by DANDI cli",
"endDate":
"2023-07-04T17:21:43.098615+02:00",
"id":
"urn:uuid:d8183a8c-418d-4b5a-99aa-3c83a768924d",
"name":
"Metadata generation",
"schemaKey":
"Activity",
"startDate":
"2023-07-04T17:21:42.896662+02:00",
"wasAssociatedWith":
[
{
"identifier":
"RRID:SCR_019009",
"name":
"DANDI Command Line Interface",
"schemaKey":
"Software",
"url":
"https://github.com/dandi/dandi-cli",
"version":
"0.55.1"
}
]
}
]
},
"modified":
"2023-07-04T15:33:31.147361+00:00",
"path":
"sub-05/sub-05_ses-20170706T115300_obj-jz2qje_behavior+ecephys.nwb",
"size":
216123507
},
{
"asset_id":
"f59dc762-f307-4c1d-b345-4224facad2f4",
"blob":
"de873856-bb99-4e01-9ff7-adb0fdf73c85",
"created":
"2023-07-04T15:46:53.919095+00:00",
"metadata":
{
"@context":
"https://raw.githubusercontent.com/dandi/schema/master/releases/0.6.4/context.json",
"access":
[
{
"schemaKey":
"AccessRequirements",
"status":
"dandi:OpenAccess"
}
],
"approach":
[
{
"name":
"behavioral approach",
"schemaKey":
"ApproachType"
},
{
"name":
"electrophysiological approach",
"schemaKey":
"ApproachType"
}
],
"blobDateModified":
"2023-07-04T15:16:04.822271+02:00",
"contentSize":
216049822,
"contentUrl":
[
"https://api.dandiarchive.org/api/assets/f59dc762-f307-4c1d-b345-4224facad2f4/download/",
"https://dandiarchive.s3.amazonaws.com/blobs/de8/738/de873856-bb99-4e01-9ff7-adb0fdf73c85"
],
"dateModified":
"2023-07-04T17:33:28.693487+02:00",
"digest":
{
"dandi:dandi-etag":
"6feebc025d6321581f721c74742bc40b-4",
"dandi:sha2-256":
"cb95ea8601e08bea8357b8c2ec5c8ae3e34db8f1653f091b9282fdfd35298140"
},
"encodingFormat":
"application/x-nwb",
"id":
"dandiasset:f59dc762-f307-4c1d-b345-4224facad2f4",
"identifier":
"f59dc762-f307-4c1d-b345-4224facad2f4",
"keywords":
[
"Neuroscience",
"Electrophysiology",
"Human",
"Awake",
"Local field potential",
"Neuronal action potential",
"Spikes",
"Medial temporal lobe",
"Hippocampus",
"Entorhinal cortex",
"Amygdala",
"Scalp EEG",
"Intracranial EEG",
"Cognitive task",
"Verbal working memory",
"Epilepsy"
],
"measurementTechnique":
[
{
"name":
"analytical technique",
"schemaKey":
"MeasurementTechniqueType"
},
{
"name":
"signal filtering technique",
"schemaKey":
"MeasurementTechniqueType"
},
{
"name":
"behavioral technique",
"schemaKey":
"MeasurementTechniqueType"
},
{
"name":
"surgical technique",
"schemaKey":
"MeasurementTechniqueType"
},
{
"name":
"spike sorting technique",
"schemaKey":
"MeasurementTechniqueType"
},
{
"name":
"multi electrode extracellular electrophysiology recording technique",
"schemaKey":
"MeasurementTechniqueType"
}
],
"path":
"sub-05/sub-05_ses-20170706T141100_behavior+ecephys.nwb",
"schemaKey":
"Asset",
"schemaVersion":
"0.6.4",
"variableMeasured":
[
{
"schemaKey":
"PropertyValue",
"value":
"Units"
},
{
"schemaKey":
"PropertyValue",
"value":
"LFP"
},
{
"schemaKey":
"PropertyValue",
"value":
"ElectricalSeries"
},
{
"schemaKey":
"PropertyValue",
"value":
"ElectrodeGroup"
},
{
"schemaKey":
"PropertyValue",
"value":
"BehavioralEvents"
},
{
"schemaKey":
"PropertyValue",
"value":
"ProcessingModule"
}
],
"wasAttributedTo":
[
{
"age":
{
"schemaKey":
"PropertyValue",
"unitText":
"ISO-8601 duration",
"value":
"P20Y",
"valueReference":
{
"schemaKey":
"PropertyValue",
"value":
"dandi:BirthReference"
}
},
"identifier":
"05",
"schemaKey":
"Participant",
"sex":
{
"identifier":
"http://purl.obolibrary.org/obo/PATO_0000383",
"name":
"Female",
"schemaKey":
"SexType"
},
"species":
{
"identifier":
"http://purl.obolibrary.org/obo/NCBITaxon_9606",
"name":
"Homo sapiens - Human",
"schemaKey":
"SpeciesType"
}
}
],
"wasGeneratedBy":
[
{
"description":
"Running experiment as described in the the experiment description",
"name":
"Acquisition session",
"schemaKey":
"Session",
"startDate":
"2017-07-06T14:11:00+02:00"
},
{
"description":
"Metadata generated by DANDI cli",
"endDate":
"2023-07-04T17:33:28.693487+02:00",
"id":
"urn:uuid:1c70265a-dc60-4af1-8f4d-e4f9a0768b70",
"name":
"Metadata generation",
"schemaKey":
"Activity",
"startDate":
"2023-07-04T17:33:28.159000+02:00",
"wasAssociatedWith":
[
{
"identifier":
"RRID:SCR_019009",
"name":
"DANDI Command Line Interface",
"schemaKey":
"Software",
"url":
"https://github.com/dandi/dandi-cli",
"version":
"0.55.1"
}
]
}
]
},
"modified":
"2023-07-04T15:46:56.358810+00:00",
"path":
"sub-05/sub-05_ses-20170706T141100_behavior+ecephys.nwb",
"size":
216049822
},
{
"asset_id":
"9556907e-ca95-48c8-89b8-cb2eddf7ea5e",
"blob":
"8878c5ff-8655-4fae-a70b-5d5d49379124",
"created":
"2023-07-04T15:58:31.497245+00:00",
"metadata":
{
"@context":
"https://raw.githubusercontent.com/dandi/schema/master/releases/0.6.4/context.json",
"access":
[
{
"schemaKey":
"AccessRequirements",
"status":
"dandi:OpenAccess"
}
],
"approach":
[
{
"name":
"behavioral approach",
"schemaKey":
"ApproachType"
},
{
"name":
"electrophysiological approach",
"schemaKey":
"ApproachType"
}
],
"blobDateModified":
"2023-07-04T15:16:40.609294+02:00",
"contentSize":
406400567,
"contentUrl":
[
"https://api.dandiarchive.org/api/assets/9556907e-ca95-48c8-89b8-cb2eddf7ea5e/download/",
"https://dandiarchive.s3.amazonaws.com/blobs/887/8c5/8878c5ff-8655-4fae-a70b-5d5d49379124"
],
"dateModified":
"2023-07-04T17:33:31.043576+02:00",
"digest":
{
"dandi:dandi-etag":
"a8c69ff0cafa28f722b8868019645eda-7",
"dandi:sha2-256":
"5cb48219db32cac70c48bd41f84101c9118ddf09daeec0092ebd6102e08923ef"
},
"encodingFormat":
"application/x-nwb",
"id":
"dandiasset:9556907e-ca95-48c8-89b8-cb2eddf7ea5e",
"identifier":
"9556907e-ca95-48c8-89b8-cb2eddf7ea5e",
"keywords":
[
"Neuroscience",
"Electrophysiology",
"Human",
"Awake",
"Local field potential",
"Neuronal action potential",
"Spikes",
"Medial temporal lobe",
"Hippocampus",
"Entorhinal cortex",
"Amygdala",
"Scalp EEG",
"Intracranial EEG",
"Cognitive task",
"Verbal working memory",
"Epilepsy"
],
"measurementTechnique":
[
{
"name":
"analytical technique",
"schemaKey":
"MeasurementTechniqueType"
},
{
"name":
"signal filtering technique",
"schemaKey":
"MeasurementTechniqueType"
},
{
"name":
"behavioral technique",
"schemaKey":
"MeasurementTechniqueType"
},
{
"name":
"surgical technique",
"schemaKey":
"MeasurementTechniqueType"
},
{
"name":
"spike sorting technique",
"schemaKey":
"MeasurementTechniqueType"
},
{
"name":
"multi electrode extracellular electrophysiology recording technique",
"schemaKey":
"MeasurementTechniqueType"
}
],
"path":
"sub-06/sub-06_ses-20140827T165900_behavior+ecephys.nwb",
"schemaKey":
"Asset",
"schemaVersion":
"0.6.4",
"variableMeasured":
[
{
"schemaKey":
"PropertyValue",
"value":
"Units"
},
{
"schemaKey":
"PropertyValue",
"value":
"LFP"
},
{
"schemaKey":
"PropertyValue",
"value":
"ElectricalSeries"
},
{
"schemaKey":
"PropertyValue",
"value":
"ElectrodeGroup"
},
{
"schemaKey":
"PropertyValue",
"value":
"BehavioralEvents"
},
{
"schemaKey":
"PropertyValue",
"value":
"ProcessingModule"
}
],
"wasAttributedTo":
[
{
"age":
{
"schemaKey":
"PropertyValue",
"unitText":
"ISO-8601 duration",
"value":
"P31Y",
"valueReference":
{
"schemaKey":
"PropertyValue",
"value":
"dandi:BirthReference"
}
},
"identifier":
"06",
"schemaKey":
"Participant",
"sex":
{
"identifier":
"http://purl.obolibrary.org/obo/PATO_0000384",
"name":
"Male",
"schemaKey":
"SexType"
},
"species":
{
"identifier":
"http://purl.obolibrary.org/obo/NCBITaxon_9606",
"name":
"Homo sapiens - Human",
"schemaKey":
"SpeciesType"
}
}
],
"wasGeneratedBy":
[
{
"description":
"Running experiment as described in the the experiment description",
"name":
"Acquisition session",
"schemaKey":
"Session",
"startDate":
"2014-08-27T16:59:00+02:00"
},
{
"description":
"Metadata generated by DANDI cli",
"endDate":
"2023-07-04T17:33:31.043576+02:00",
"id":
"urn:uuid:b7aa2328-7fac-44c7-b800-7bb33999f600",
"name":
"Metadata generation",
"schemaKey":
"Activity",
"startDate":
"2023-07-04T17:33:30.838410+02:00",
"wasAssociatedWith":
[
{
"identifier":
"RRID:SCR_019009",
"name":
"DANDI Command Line Interface",
"schemaKey":
"Software",
"url":
"https://github.com/dandi/dandi-cli",
"version":
"0.55.1"
}
]
}
]
},
"modified":
"2023-07-04T15:58:35.518036+00:00",
"path":
"sub-06/sub-06_ses-20140827T165900_behavior+ecephys.nwb",
"size":
406400567
}
]